flopferret/__init__.py
flopferret/board_texture.py
flopferret/hand_range.py
flopferret/main_window.py
flopferret/percent_display.py
flopferret/range_selector.py
flopferret/saved_ranges.py
flopferret-0.1.4.dist-info/LICENSE
flopferret-0.1.4.dist-info/METADATA
flopferret-0.1.4.dist-info/WHEEL
flopferret-0.1.4.dist-info/entry_points.txt
flopferret-0.1.4.dist-info/top_level.txt
flopferret-0.1.4.dist-info/RECORD
