Metadata-Version: 2.1
Name: flopferret
Version: 0.1.4
Summary: A Texas Hold'em board texture analyzer
Home-page: https://github.com/JulianAndrews/pyeval7
License: MIT
Keywords: poker equity
Platform: UNKNOWN
Classifier: Development Status :: 4 - Beta
Classifier: Intended Audience :: End Users/Desktop
Classifier: License :: OSI Approved :: MIT License
Classifier: Programming Language :: Python :: 3.6
Classifier: Programming Language :: Python :: 3.7
Classifier: Programming Language :: Python :: 3.8
Classifier: Topic :: Games/Entertainment
Requires-Dist: pyxdg
Requires-Dist: eval7 (>=0.1.6)
Requires-Dist: PyQt5
